BESMNNCORRECT/BESMNNCORRECT.py
BESMNNCORRECT/__init__.py
besmnncorrect-0.1.1.dist-info/licenses/LICENSE
besmnncorrect-0.1.1.dist-info/METADATA
besmnncorrect-0.1.1.dist-info/WHEEL
besmnncorrect-0.1.1.dist-info/top_level.txt
besmnncorrect-0.1.1.dist-info/RECORD
