Metadata-Version: 2.4
Name: besmnncorrect
Version: 0.1.1
Summary: A batch effect correction method for subregional radiomics dataset
Author: Pan Ziqi
License: file="LICENSE"
Requires-Python: >=3.9
License-File: LICENSE
Requires-Dist: numpy>=1.23.0
Requires-Dist: pandas>=2.2.3
Requires-Dist: scikit_learn>=1.6.1
Dynamic: license-file
